{
  "id": "gid://shopify/Product/7634433605805",
  "title": "Unisex Hoodie",
  "description": "Made to be stylish as well as comfortable, the Independent Trading Co. SS4500 personalized hooded sweatshirt delivers on all fronts. Made from an 80% - 20% cotton/polyester blend, it strikes the perfect balance between cozy and stretchy. What's more, the metal eyelets for your hoodie drawstrings add durability while the jersey-lined hood keeps you nice & warm when it’s needed. .: 80% cotton, 20 % polyester fleece with 100% cotton face (fiber content may vary for different colors).: Medium-heavy fabric (8.5 oz /yd² (280 g/m²)).: Regular fit.: Tear-away label",
  "descriptionHtml": "<p>Made to be stylish as well as comfortable, the Independent Trading Co. SS4500 personalized hooded sweatshirt delivers on all fronts. Made from an 80% - 20% cotton/polyester blend, it strikes the perfect balance between cozy and stretchy. What's more, the metal eyelets for your hoodie drawstrings add durability while the jersey-lined hood keeps you nice &amp; warm when it’s needed. </p>\n<p>.: 80% cotton, 20</p>\n<p> % polyester fleece with 100% cotton face (fiber content may vary for different colors)<br>.: Medium-heavy fabric (8.5 oz /yd² (280 g/m²))<br>.: Regular fit<br>.: Tear-away label</p>",
  "availableForSale": true,
  "handle": "unisex-hoodie",
  "productType": "Hoodie",
  "tags": [
    "DTG",
    "Hoodies",
    "Men's Clothing",
    "Unisex",
    "Women's Clothing"
  ],
  "vendor": "Printify",
  "priceRange": {
    "maxVariantPrice": {
      "amount": "32.09",
      "currencyCode": "CAD"
    },
    "minVariantPrice": {
      "amount": "28.52",
      "currencyCode": "CAD"
    }
  },
  "compareAtPriceRange": {
    "maxVariantPrice": {
      "amount": "45.0",
      "currencyCode": "CAD"
    },
    "minVariantPrice": {
      "amount": "45.0",
      "currencyCode": "CAD"
    }
  },
  "images": [
    {
      "id": "gid://shopify/ProductImage/34359628497069",
      "url": "https://cdn.shopify.com/s/files/1/0654/2458/8973/files/15432182594235543675_2048_1180x400.jpg?v=1713378389"
    },
    {
      "id": "gid://shopify/ProductImage/34359628529837",
      "url": "https://cdn.shopify.com/s/files/1/0654/2458/8973/files/3242859021909173943_2048_1180x400.jpg?v=1713378389"
    }
  ],
  "options": [
    {
      "id": "gid://shopify/ProductOption/9749761556653",
      "name": "Color",
      "values": [
        "Black",
        "White"
      ]
    },
    {
      "id": "gid://shopify/ProductOption/9749761589421",
      "name": "Size",
      "values": [
        "S",
        "M",
        "L",
        "XL",
        "2XL"
      ]
    }
  ],
  "requiresSellingPlan": false,
  "onlineStoreUrl": "https://shop.reactivapp.com/products/unisex-hoodie",
  "media": [
    {
      "mediaContentType": "IMAGE",
      "image": {
        "url": "https://cdn.shopify.com/s/files/1/0654/2458/8973/files/15432182594235543675_2048_1180x400.jpg?v=1713378389",
        "id": "gid://shopify/ImageSource/26753117192365",
        "altText": null,
        "width": 2048,
        "height": 2048
      }
    },
    {
      "mediaContentType": "IMAGE",
      "image": {
        "url": "https://cdn.shopify.com/s/files/1/0654/2458/8973/files/3242859021909173943_2048_1180x400.jpg?v=1713378389",
        "id": "gid://shopify/ImageSource/26753117225133",
        "altText": null,
        "width": 2048,
        "height": 2048
      }
    }
  ],
  "variants": [
    {
      "id": "gid://shopify/ProductVariant/43098641498285",
      "title": "Black / S",
      "quantityAvailable": 10,
      "availableForSale": true,
      "currentlyNotInStock": false,
      "price": {
        "amount": "28.96",
        "currencyCode": "CAD"
      },
      "compareAtPrice": {
        "amount": "45.0",
        "currencyCode": "CAD"
      },
      "sku": "19958964877259077185",
      "selectedOptions": [
        {
          "name": "Color",
          "value": "Black"
        },
        {
          "name": "Size",
          "value": "S"
        }
      ],
      "image": {
        "id": "gid://shopify/ProductImage/34359628497069",
        "url": "https://cdn.shopify.com/s/files/1/0654/2458/8973/files/15432182594235543675_2048_1180x400.jpg?v=1713378389"
      },
      "product": {
        "id": "gid://shopify/Product/7634433605805",
        "handle": "unisex-hoodie",
        "options": [
          {
            "id": "gid://shopify/ProductOption/9749761556653",
            "name": "Color",
            "values": [
              "Black",
              "White"
            ]
          },
          {
            "id": "gid://shopify/ProductOption/9749761589421",
            "name": "Size",
            "values": [
              "S",
              "M",
              "L",
              "XL",
              "2XL"
            ]
          }
        ]
      }
    }
  ]
}